piedpiper_engine/__init__.py
piedpiper_engine/__main__.py
piedpiper_engine/engine.py
piedpiper_engine/engine_manager_thread.py
piedpiper_engine-0.0.2.dist-info/METADATA
piedpiper_engine-0.0.2.dist-info/WHEEL
piedpiper_engine-0.0.2.dist-info/licenses/LICENSE
piedpiper_engine-0.0.2.dist-info/RECORD
